{
  "entityType": "ENTITY_TYPE_PARTIAL",
  "hd": 10,
  "proficiencies": [
    "PROFICIENCY_ARMOR_HEAVY",
    "PROFICIENCY_ARMOR_MEDIUM",
    "PROFICIENCY_ARMOR_LIGHT",
    "PROFICIENCY_SHIELD",
    "PROFICIENCY_WEAPON_MARTIAL",
    "PROFICIENCY_WEAPON_SIMPLE",
    "PROFICIENCY_SAVING_THROW_STRENGTH",
    "PROFICIENCY_SAVING_THROW_CONSTITUTION"
  ],
  "classType": "CLASS_TYPE_FIGHTER",
  "actions": [
    {
      "id": "act-fighter-second-wind",
      "actionType": "COMBAT_ACTION_TYPE_SPELL_LIKE_ABILITY",
      "script": "at-fighter-second-wind",
      "range": 0,
      "parameters": {},
      "cooldown": 120,
      "bonus": true,
      "requirements": {
        "classType": "CLASS_TYPE_FIGHTER",
        "level": 1
      }
    },
    {
      "id": "act-fighter-action-surge",
      "actionType": "COMBAT_ACTION_TYPE_SPELL_LIKE_ABILITY",
      "script": "at-fighter-action-surge",
      "range": 0,
      "parameters": {},
      "cooldown": 120,
      "bonus": true,
      "requirements": {
        "classType": "CLASS_TYPE_FIGHTER",
        "level": 2
      }
    }
  ]
}
